mybasic/__init__.py
mybasic/functions.py
mybasic/greet.py
mybasic-0.1.dist-info/METADATA
mybasic-0.1.dist-info/WHEEL
mybasic-0.1.dist-info/top_level.txt
mybasic-0.1.dist-info/RECORD
