Metadata-Version: 2.1
Name: mybasic
Version: 0.1
Summary: Testing installation of Package
Home-page: https://github.com/JonahYeoh
Author: auth
Author-email: auth@gmail.com
License: MIT
Platform: UNKNOWN
